{
  "id": "48757756-d677-4c21-a115-a64f8eb2d129",
  "prevId": "b1937769-ae91-4f04-8ca4-c45cdd086ba6",
  "version": "7",
  "dialect": "postgresql",
  "tables": {
    "public.ask_turns": {
      "name": "ask_turns",
      "schema": "",
      "columns": {
        "id": {
          "name": "id",
          "type": "uuid",
          "primaryKey": true,
          "notNull": true,
          "default": "gen_random_uuid()"
        },
        "user_id": {
          "name": "user_id",
          "type": "uuid",
          "primaryKey": false,
          "notNull": true
        },
        "question_text": {
          "name": "question_text",
          "type": "text",
          "primaryKey": false,
          "notNull": true
        },
        "answer_text": {
          "name": "answer_text",
          "type": "text",
          "primaryKey": false,
          "notNull": false
        },
        "sources": {
          "name": "sources",
          "type": "jsonb",
          "primaryKey": false,
          "notNull": true
        },
        "input_kind": {
          "name": "input_kind",
          "type": "text",
          "primaryKey": false,
          "notNull": true
        },
        "error": {
          "name": "error",
          "type": "jsonb",
          "primaryKey": false,
          "notNull": false
        },
        "created_at": {
          "name": "created_at",
          "type": "timestamp with time zone",
          "primaryKey": false,
          "notNull": true,
          "default": "now()"
        }
      },
      "indexes": {
        "ix_ask_turns_user_created": {
          "name": "ix_ask_turns_user_created",
          "columns": [
            {
              "expression": "user_id",
              "isExpression": false,
              "asc": true,
              "nulls": "last"
            },
            {
              "expression": "created_at",
              "isExpression": false,
              "asc": true,
              "nulls": "last"
            }
          ],
          "isUnique": false,
          "concurrently": false,
          "method": "btree",
          "with": {}
        }
      },
      "foreignKeys": {
        "ask_turns_user_id_users_id_fk": {
          "name": "ask_turns_user_id_users_id_fk",
          "tableFrom": "ask_turns",
          "tableTo": "users",
          "columnsFrom": [
            "user_id"
          ],
          "columnsTo": [
            "id"
          ],
          "onDelete": "cascade",
          "onUpdate": "no action"
        }
      },
      "compositePrimaryKeys": {},
      "uniqueConstraints": {},
      "policies": {},
      "checkConstraints": {},
      "isRLSEnabled": false
    },
    "public.calendar_connections": {
      "name": "calendar_connections",
      "schema": "",
      "columns": {
        "id": {
          "name": "id",
          "type": "uuid",
          "primaryKey": true,
          "notNull": true,
          "default": "gen_random_uuid()"
        },
        "user_id": {
          "name": "user_id",
          "type": "uuid",
          "primaryKey": false,
          "notNull": true
        },
        "provider": {
          "name": "provider",
          "type": "text",
          "primaryKey": false,
          "notNull": true
        },
        "is_primary": {
          "name": "is_primary",
          "type": "boolean",
          "primaryKey": false,
          "notNull": true,
          "default": false
        },
        "google_access_token": {
          "name": "google_access_token",
          "type": "text",
          "primaryKey": false,
          "notNull": false
        },
        "google_refresh_token": {
          "name": "google_refresh_token",
          "type": "text",
          "primaryKey": false,
          "notNull": false
        },
        "google_token_expires_at": {
          "name": "google_token_expires_at",
          "type": "timestamp with time zone",
          "primaryKey": false,
          "notNull": false
        },
        "google_email": {
          "name": "google_email",
          "type": "text",
          "primaryKey": false,
          "notNull": false
        },
        "apple_calendar_ids": {
          "name": "apple_calendar_ids",
          "type": "jsonb",
          "primaryKey": false,
          "notNull": false
        },
        "last_synced_at": {
          "name": "last_synced_at",
          "type": "timestamp with time zone",
          "primaryKey": false,
          "notNull": false
        },
        "sync_cursor": {
          "name": "sync_cursor",
          "type": "text",
          "primaryKey": false,
          "notNull": false
        },
        "created_at": {
          "name": "created_at",
          "type": "timestamp with time zone",
          "primaryKey": false,
          "notNull": true,
          "default": "now()"
        },
        "updated_at": {
          "name": "updated_at",
          "type": "timestamp with time zone",
          "primaryKey": false,
          "notNull": true,
          "default": "now()"
        }
      },
      "indexes": {
        "ix_cal_conn_user": {
          "name": "ix_cal_conn_user",
          "columns": [
            {
              "expression": "user_id",
              "isExpression": false,
              "asc": true,
              "nulls": "last"
            }
          ],
          "isUnique": false,
          "concurrently": false,
          "method": "btree",
          "with": {}
        },
        "ix_cal_conn_user_provider": {
          "name": "ix_cal_conn_user_provider",
          "columns": [
            {
              "expression": "user_id",
              "isExpression": false,
              "asc": true,
              "nulls": "last"
            },
            {
              "expression": "provider",
              "isExpression": false,
              "asc": true,
              "nulls": "last"
            }
          ],
          "isUnique": false,
          "concurrently": false,
          "method": "btree",
          "with": {}
        }
      },
      "foreignKeys": {
        "calendar_connections_user_id_users_id_fk": {
          "name": "calendar_connections_user_id_users_id_fk",
          "tableFrom": "calendar_connections",
          "tableTo": "users",
          "columnsFrom": [
            "user_id"
          ],
          "columnsTo": [
            "id"
          ],
          "onDelete": "cascade",
          "onUpdate": "no action"
        }
      },
      "compositePrimaryKeys": {},
      "uniqueConstraints": {},
      "policies": {},
      "checkConstraints": {},
      "isRLSEnabled": false
    },
    "public.dumps": {
      "name": "dumps",
      "schema": "",
      "columns": {
        "id": {
          "name": "id",
          "type": "uuid",
          "primaryKey": true,
          "notNull": true,
          "default": "gen_random_uuid()"
        },
        "user_id": {
          "name": "user_id",
          "type": "uuid",
          "primaryKey": false,
          "notNull": true
        },
        "text": {
          "name": "text",
          "type": "text",
          "primaryKey": false,
          "notNull": true
        },
        "polished_text": {
          "name": "polished_text",
          "type": "text",
          "primaryKey": false,
          "notNull": false
        },
        "status": {
          "name": "status",
          "type": "text",
          "primaryKey": false,
          "notNull": true,
          "default": "'processing'"
        },
        "last_error": {
          "name": "last_error",
          "type": "text",
          "primaryKey": false,
          "notNull": false
        },
        "created_at": {
          "name": "created_at",
          "type": "timestamp with time zone",
          "primaryKey": false,
          "notNull": true,
          "default": "now()"
        },
        "additional_context": {
          "name": "additional_context",
          "type": "jsonb",
          "primaryKey": false,
          "notNull": false
        },
        "agent_assumptions": {
          "name": "agent_assumptions",
          "type": "jsonb",
          "primaryKey": false,
          "notNull": false
        },
        "audio_key": {
          "name": "audio_key",
          "type": "text",
          "primaryKey": false,
          "notNull": false
        }
      },
      "indexes": {
        "ix_dumps_user_id": {
          "name": "ix_dumps_user_id",
          "columns": [
            {
              "expression": "user_id",
              "isExpression": false,
              "asc": true,
              "nulls": "last"
            }
          ],
          "isUnique": false,
          "concurrently": false,
          "method": "btree",
          "with": {}
        }
      },
      "foreignKeys": {
        "dumps_user_id_users_id_fk": {
          "name": "dumps_user_id_users_id_fk",
          "tableFrom": "dumps",
          "tableTo": "users",
          "columnsFrom": [
            "user_id"
          ],
          "columnsTo": [
            "id"
          ],
          "onDelete": "cascade",
          "onUpdate": "no action"
        }
      },
      "compositePrimaryKeys": {},
      "uniqueConstraints": {},
      "policies": {},
      "checkConstraints": {},
      "isRLSEnabled": false
    },
    "public.extracts": {
      "name": "extracts",
      "schema": "",
      "columns": {
        "id": {
          "name": "id",
          "type": "uuid",
          "primaryKey": true,
          "notNull": true,
          "default": "gen_random_uuid()"
        },
        "user_id": {
          "name": "user_id",
          "type": "uuid",
          "primaryKey": false,
          "notNull": true
        },
        "dump_id": {
          "name": "dump_id",
          "type": "uuid",
          "primaryKey": false,
          "notNull": false
        },
        "source": {
          "name": "source",
          "type": "text",
          "primaryKey": false,
          "notNull": true,
          "default": "'dump'"
        },
        "text": {
          "name": "text",
          "type": "text",
          "primaryKey": false,
          "notNull": true
        },
        "original_text": {
          "name": "original_text",
          "type": "text",
          "primaryKey": false,
          "notNull": true
        },
        "status": {
          "name": "status",
          "type": "text",
          "primaryKey": false,
          "notNull": true
        },
        "tone": {
          "name": "tone",
          "type": "text",
          "primaryKey": false,
          "notNull": true
        },
        "urgency": {
          "name": "urgency",
          "type": "text",
          "primaryKey": false,
          "notNull": true
        },
        "batch_key": {
          "name": "batch_key",
          "type": "text",
          "primaryKey": false,
          "notNull": false
        },
        "due_at": {
          "name": "due_at",
          "type": "timestamp with time zone",
          "primaryKey": false,
          "notNull": false
        },
        "period_start": {
          "name": "period_start",
          "type": "timestamp with time zone",
          "primaryKey": false,
          "notNull": false
        },
        "period_end": {
          "name": "period_end",
          "type": "timestamp with time zone",
          "primaryKey": false,
          "notNull": false
        },
        "period_label": {
          "name": "period_label",
          "type": "text",
          "primaryKey": false,
          "notNull": false
        },
        "timezone_pending": {
          "name": "timezone_pending",
          "type": "boolean",
          "primaryKey": false,
          "notNull": true,
          "default": false
        },
        "snoozed_until": {
          "name": "snoozed_until",
          "type": "timestamp with time zone",
          "primaryKey": false,
          "notNull": false
        },
        "done_at": {
          "name": "done_at",
          "type": "timestamp with time zone",
          "primaryKey": false,
          "notNull": false
        },
        "dismissed_at": {
          "name": "dismissed_at",
          "type": "timestamp with time zone",
          "primaryKey": false,
          "notNull": false
        },
        "pem_note": {
          "name": "pem_note",
          "type": "text",
          "primaryKey": false,
          "notNull": false
        },
        "recommended_at": {
          "name": "recommended_at",
          "type": "timestamp with time zone",
          "primaryKey": false,
          "notNull": false
        },
        "draft_text": {
          "name": "draft_text",
          "type": "text",
          "primaryKey": false,
          "notNull": false
        },
        "external_event_id": {
          "name": "external_event_id",
          "type": "text",
          "primaryKey": false,
          "notNull": false
        },
        "calendar_connection_id": {
          "name": "calendar_connection_id",
          "type": "uuid",
          "primaryKey": false,
          "notNull": false
        },
        "event_start_at": {
          "name": "event_start_at",
          "type": "timestamp with time zone",
          "primaryKey": false,
          "notNull": false
        },
        "event_end_at": {
          "name": "event_end_at",
          "type": "timestamp with time zone",
          "primaryKey": false,
          "notNull": false
        },
        "event_location": {
          "name": "event_location",
          "type": "text",
          "primaryKey": false,
          "notNull": false
        },
        "created_at": {
          "name": "created_at",
          "type": "timestamp with time zone",
          "primaryKey": false,
          "notNull": true,
          "default": "now()"
        },
        "updated_at": {
          "name": "updated_at",
          "type": "timestamp with time zone",
          "primaryKey": false,
          "notNull": true,
          "default": "now()"
        }
      },
      "indexes": {
        "ix_extracts_user_id": {
          "name": "ix_extracts_user_id",
          "columns": [
            {
              "expression": "user_id",
              "isExpression": false,
              "asc": true,
              "nulls": "last"
            }
          ],
          "isUnique": false,
          "concurrently": false,
          "method": "btree",
          "with": {}
        },
        "ix_extracts_dump_id": {
          "name": "ix_extracts_dump_id",
          "columns": [
            {
              "expression": "dump_id",
              "isExpression": false,
              "asc": true,
              "nulls": "last"
            }
          ],
          "isUnique": false,
          "concurrently": false,
          "method": "btree",
          "with": {}
        },
        "ix_extracts_user_status_urgency": {
          "name": "ix_extracts_user_status_urgency",
          "columns": [
            {
              "expression": "user_id",
              "isExpression": false,
              "asc": true,
              "nulls": "last"
            },
            {
              "expression": "status",
              "isExpression": false,
              "asc": true,
              "nulls": "last"
            },
            {
              "expression": "urgency",
              "isExpression": false,
              "asc": true,
              "nulls": "last"
            }
          ],
          "isUnique": false,
          "concurrently": false,
          "method": "btree",
          "with": {}
        },
        "ix_extracts_batch": {
          "name": "ix_extracts_batch",
          "columns": [
            {
              "expression": "user_id",
              "isExpression": false,
              "asc": true,
              "nulls": "last"
            },
            {
              "expression": "batch_key",
              "isExpression": false,
              "asc": true,
              "nulls": "last"
            }
          ],
          "isUnique": false,
          "concurrently": false,
          "method": "btree",
          "with": {}
        },
        "uq_extracts_calendar": {
          "name": "uq_extracts_calendar",
          "columns": [
            {
              "expression": "calendar_connection_id",
              "isExpression": false,
              "asc": true,
              "nulls": "last"
            },
            {
              "expression": "external_event_id",
              "isExpression": false,
              "asc": true,
              "nulls": "last"
            }
          ],
          "isUnique": true,
          "concurrently": false,
          "method": "btree",
          "with": {}
        }
      },
      "foreignKeys": {
        "extracts_user_id_users_id_fk": {
          "name": "extracts_user_id_users_id_fk",
          "tableFrom": "extracts",
          "tableTo": "users",
          "columnsFrom": [
            "user_id"
          ],
          "columnsTo": [
            "id"
          ],
          "onDelete": "cascade",
          "onUpdate": "no action"
        },
        "extracts_dump_id_dumps_id_fk": {
          "name": "extracts_dump_id_dumps_id_fk",
          "tableFrom": "extracts",
          "tableTo": "dumps",
          "columnsFrom": [
            "dump_id"
          ],
          "columnsTo": [
            "id"
          ],
          "onDelete": "cascade",
          "onUpdate": "no action"
        },
        "extracts_calendar_connection_id_calendar_connections_id_fk": {
          "name": "extracts_calendar_connection_id_calendar_connections_id_fk",
          "tableFrom": "extracts",
          "tableTo": "calendar_connections",
          "columnsFrom": [
            "calendar_connection_id"
          ],
          "columnsTo": [
            "id"
          ],
          "onDelete": "set null",
          "onUpdate": "no action"
        }
      },
      "compositePrimaryKeys": {},
      "uniqueConstraints": {},
      "policies": {},
      "checkConstraints": {},
      "isRLSEnabled": false
    },
    "public.follow_ups": {
      "name": "follow_ups",
      "schema": "",
      "columns": {
        "id": {
          "name": "id",
          "type": "uuid",
          "primaryKey": true,
          "notNull": true,
          "default": "gen_random_uuid()"
        },
        "user_id": {
          "name": "user_id",
          "type": "uuid",
          "primaryKey": false,
          "notNull": true
        },
        "extract_id": {
          "name": "extract_id",
          "type": "uuid",
          "primaryKey": false,
          "notNull": true
        },
        "note": {
          "name": "note",
          "type": "text",
          "primaryKey": false,
          "notNull": false
        },
        "recommended_at": {
          "name": "recommended_at",
          "type": "timestamp with time zone",
          "primaryKey": false,
          "notNull": false
        },
        "source_dump_id": {
          "name": "source_dump_id",
          "type": "uuid",
          "primaryKey": false,
          "notNull": false
        },
        "created_at": {
          "name": "created_at",
          "type": "timestamp with time zone",
          "primaryKey": false,
          "notNull": true,
          "default": "now()"
        },
        "updated_at": {
          "name": "updated_at",
          "type": "timestamp with time zone",
          "primaryKey": false,
          "notNull": true,
          "default": "now()"
        }
      },
      "indexes": {
        "ix_follow_ups_user_id": {
          "name": "ix_follow_ups_user_id",
          "columns": [
            {
              "expression": "user_id",
              "isExpression": false,
              "asc": true,
              "nulls": "last"
            }
          ],
          "isUnique": false,
          "concurrently": false,
          "method": "btree",
          "with": {}
        },
        "ix_follow_ups_recommended_at": {
          "name": "ix_follow_ups_recommended_at",
          "columns": [
            {
              "expression": "user_id",
              "isExpression": false,
              "asc": true,
              "nulls": "last"
            },
            {
              "expression": "recommended_at",
              "isExpression": false,
              "asc": true,
              "nulls": "last"
            }
          ],
          "isUnique": false,
          "concurrently": false,
          "method": "btree",
          "with": {}
        }
      },
      "foreignKeys": {
        "follow_ups_user_id_users_id_fk": {
          "name": "follow_ups_user_id_users_id_fk",
          "tableFrom": "follow_ups",
          "tableTo": "users",
          "columnsFrom": [
            "user_id"
          ],
          "columnsTo": [
            "id"
          ],
          "onDelete": "cascade",
          "onUpdate": "no action"
        },
        "follow_ups_extract_id_extracts_id_fk": {
          "name": "follow_ups_extract_id_extracts_id_fk",
          "tableFrom": "follow_ups",
          "tableTo": "extracts",
          "columnsFrom": [
            "extract_id"
          ],
          "columnsTo": [
            "id"
          ],
          "onDelete": "cascade",
          "onUpdate": "no action"
        },
        "follow_ups_source_dump_id_dumps_id_fk": {
          "name": "follow_ups_source_dump_id_dumps_id_fk",
          "tableFrom": "follow_ups",
          "tableTo": "dumps",
          "columnsFrom": [
            "source_dump_id"
          ],
          "columnsTo": [
            "id"
          ],
          "onDelete": "set null",
          "onUpdate": "no action"
        }
      },
      "compositePrimaryKeys": {},
      "uniqueConstraints": {
        "follow_ups_extract_id_unique": {
          "name": "follow_ups_extract_id_unique",
          "nullsNotDistinct": false,
          "columns": [
            "extract_id"
          ]
        }
      },
      "policies": {},
      "checkConstraints": {},
      "isRLSEnabled": false
    },
    "public.logs": {
      "name": "logs",
      "schema": "",
      "columns": {
        "id": {
          "name": "id",
          "type": "uuid",
          "primaryKey": true,
          "notNull": true,
          "default": "gen_random_uuid()"
        },
        "user_id": {
          "name": "user_id",
          "type": "uuid",
          "primaryKey": false,
          "notNull": true
        },
        "type": {
          "name": "type",
          "type": "text",
          "primaryKey": false,
          "notNull": true
        },
        "extract_id": {
          "name": "extract_id",
          "type": "uuid",
          "primaryKey": false,
          "notNull": false
        },
        "dump_id": {
          "name": "dump_id",
          "type": "uuid",
          "primaryKey": false,
          "notNull": false
        },
        "is_agent": {
          "name": "is_agent",
          "type": "boolean",
          "primaryKey": false,
          "notNull": true,
          "default": false
        },
        "pem_note": {
          "name": "pem_note",
          "type": "text",
          "primaryKey": false,
          "notNull": false
        },
        "payload": {
          "name": "payload",
          "type": "jsonb",
          "primaryKey": false,
          "notNull": false
        },
        "error": {
          "name": "error",
          "type": "jsonb",
          "primaryKey": false,
          "notNull": false
        },
        "created_at": {
          "name": "created_at",
          "type": "timestamp with time zone",
          "primaryKey": false,
          "notNull": true,
          "default": "now()"
        }
      },
      "indexes": {
        "ix_logs_user_created": {
          "name": "ix_logs_user_created",
          "columns": [
            {
              "expression": "user_id",
              "isExpression": false,
              "asc": true,
              "nulls": "last"
            },
            {
              "expression": "created_at",
              "isExpression": false,
              "asc": true,
              "nulls": "last"
            }
          ],
          "isUnique": false,
          "concurrently": false,
          "method": "btree",
          "with": {}
        },
        "ix_logs_extract": {
          "name": "ix_logs_extract",
          "columns": [
            {
              "expression": "extract_id",
              "isExpression": false,
              "asc": true,
              "nulls": "last"
            }
          ],
          "isUnique": false,
          "concurrently": false,
          "method": "btree",
          "with": {}
        },
        "ix_logs_dump": {
          "name": "ix_logs_dump",
          "columns": [
            {
              "expression": "dump_id",
              "isExpression": false,
              "asc": true,
              "nulls": "last"
            }
          ],
          "isUnique": false,
          "concurrently": false,
          "method": "btree",
          "with": {}
        },
        "ix_logs_type": {
          "name": "ix_logs_type",
          "columns": [
            {
              "expression": "user_id",
              "isExpression": false,
              "asc": true,
              "nulls": "last"
            },
            {
              "expression": "type",
              "isExpression": false,
              "asc": true,
              "nulls": "last"
            }
          ],
          "isUnique": false,
          "concurrently": false,
          "method": "btree",
          "with": {}
        }
      },
      "foreignKeys": {
        "logs_user_id_users_id_fk": {
          "name": "logs_user_id_users_id_fk",
          "tableFrom": "logs",
          "tableTo": "users",
          "columnsFrom": [
            "user_id"
          ],
          "columnsTo": [
            "id"
          ],
          "onDelete": "cascade",
          "onUpdate": "no action"
        },
        "logs_extract_id_extracts_id_fk": {
          "name": "logs_extract_id_extracts_id_fk",
          "tableFrom": "logs",
          "tableTo": "extracts",
          "columnsFrom": [
            "extract_id"
          ],
          "columnsTo": [
            "id"
          ],
          "onDelete": "set null",
          "onUpdate": "no action"
        },
        "logs_dump_id_dumps_id_fk": {
          "name": "logs_dump_id_dumps_id_fk",
          "tableFrom": "logs",
          "tableTo": "dumps",
          "columnsFrom": [
            "dump_id"
          ],
          "columnsTo": [
            "id"
          ],
          "onDelete": "set null",
          "onUpdate": "no action"
        }
      },
      "compositePrimaryKeys": {},
      "uniqueConstraints": {},
      "policies": {},
      "checkConstraints": {},
      "isRLSEnabled": false
    },
    "public.memory_facts": {
      "name": "memory_facts",
      "schema": "",
      "columns": {
        "id": {
          "name": "id",
          "type": "uuid",
          "primaryKey": true,
          "notNull": true,
          "default": "gen_random_uuid()"
        },
        "user_id": {
          "name": "user_id",
          "type": "uuid",
          "primaryKey": false,
          "notNull": true
        },
        "memory_key": {
          "name": "memory_key",
          "type": "text",
          "primaryKey": false,
          "notNull": true
        },
        "note": {
          "name": "note",
          "type": "text",
          "primaryKey": false,
          "notNull": true
        },
        "learned_at": {
          "name": "learned_at",
          "type": "timestamp with time zone",
          "primaryKey": false,
          "notNull": true,
          "default": "now()"
        },
        "source_dump_id": {
          "name": "source_dump_id",
          "type": "uuid",
          "primaryKey": false,
          "notNull": false
        },
        "status": {
          "name": "status",
          "type": "text",
          "primaryKey": false,
          "notNull": true
        },
        "provenance": {
          "name": "provenance",
          "type": "text",
          "primaryKey": false,
          "notNull": false
        },
        "created_at": {
          "name": "created_at",
          "type": "timestamp with time zone",
          "primaryKey": false,
          "notNull": true,
          "default": "now()"
        }
      },
      "indexes": {
        "ix_memory_facts_user_id": {
          "name": "ix_memory_facts_user_id",
          "columns": [
            {
              "expression": "user_id",
              "isExpression": false,
              "asc": true,
              "nulls": "last"
            }
          ],
          "isUnique": false,
          "concurrently": false,
          "method": "btree",
          "with": {}
        },
        "ix_memory_facts_user_status_learned": {
          "name": "ix_memory_facts_user_status_learned",
          "columns": [
            {
              "expression": "user_id",
              "isExpression": false,
              "asc": true,
              "nulls": "last"
            },
            {
              "expression": "status",
              "isExpression": false,
              "asc": true,
              "nulls": "last"
            },
            {
              "expression": "learned_at",
              "isExpression": false,
              "asc": true,
              "nulls": "last"
            }
          ],
          "isUnique": false,
          "concurrently": false,
          "method": "btree",
          "with": {}
        },
        "ix_memory_facts_memory_key": {
          "name": "ix_memory_facts_memory_key",
          "columns": [
            {
              "expression": "user_id",
              "isExpression": false,
              "asc": true,
              "nulls": "last"
            },
            {
              "expression": "memory_key",
              "isExpression": false,
              "asc": true,
              "nulls": "last"
            }
          ],
          "isUnique": false,
          "concurrently": false,
          "method": "btree",
          "with": {}
        }
      },
      "foreignKeys": {
        "memory_facts_user_id_users_id_fk": {
          "name": "memory_facts_user_id_users_id_fk",
          "tableFrom": "memory_facts",
          "tableTo": "users",
          "columnsFrom": [
            "user_id"
          ],
          "columnsTo": [
            "id"
          ],
          "onDelete": "cascade",
          "onUpdate": "no action"
        },
        "memory_facts_source_dump_id_dumps_id_fk": {
          "name": "memory_facts_source_dump_id_dumps_id_fk",
          "tableFrom": "memory_facts",
          "tableTo": "dumps",
          "columnsFrom": [
            "source_dump_id"
          ],
          "columnsTo": [
            "id"
          ],
          "onDelete": "set null",
          "onUpdate": "no action"
        }
      },
      "compositePrimaryKeys": {},
      "uniqueConstraints": {},
      "policies": {},
      "checkConstraints": {},
      "isRLSEnabled": false
    },
    "public.users": {
      "name": "users",
      "schema": "",
      "columns": {
        "id": {
          "name": "id",
          "type": "uuid",
          "primaryKey": true,
          "notNull": true,
          "default": "gen_random_uuid()"
        },
        "clerk_id": {
          "name": "clerk_id",
          "type": "text",
          "primaryKey": false,
          "notNull": true
        },
        "email": {
          "name": "email",
          "type": "text",
          "primaryKey": false,
          "notNull": false
        },
        "name": {
          "name": "name",
          "type": "text",
          "primaryKey": false,
          "notNull": false
        },
        "push_token": {
          "name": "push_token",
          "type": "text",
          "primaryKey": false,
          "notNull": false
        },
        "timezone": {
          "name": "timezone",
          "type": "text",
          "primaryKey": false,
          "notNull": false
        },
        "created_at": {
          "name": "created_at",
          "type": "timestamp with time zone",
          "primaryKey": false,
          "notNull": true,
          "default": "now()"
        }
      },
      "indexes": {},
      "foreignKeys": {},
      "compositePrimaryKeys": {},
      "uniqueConstraints": {
        "users_clerk_id_unique": {
          "name": "users_clerk_id_unique",
          "nullsNotDistinct": false,
          "columns": [
            "clerk_id"
          ]
        }
      },
      "policies": {},
      "checkConstraints": {},
      "isRLSEnabled": false
    }
  },
  "enums": {},
  "schemas": {},
  "sequences": {},
  "roles": {},
  "policies": {},
  "views": {},
  "_meta": {
    "columns": {},
    "schemas": {},
    "tables": {}
  }
}